{"0": "Adventure_San_Mart\u00edn_ingles", "1": "Aldea_Magica", "2": "Animal_Park", "3": "Animal_Park_ingles", "4": "Balneario_Zu\u00f1ag", "5": "Bellavista_camino", "6": "Bellavista_trail", "7": "Bridge_jumping", "8": "Bridges", "9": "Cafe_Giratorio", "10": "Cafe_Giratorio_horario", "11": "Canyoning", "12": "Canyoning_ingles", "13": "Cavernas_Sigsi_Huayco", "14": "Caverns_Sigsi_Huayco_ingles", "15": "Coffee_Turning_giratorio", "16": "Columpios", "17": "Cristo_Redentor", "18": "Cristo_Redentor_ingles", "19": "Dinosaurios_Park", "20": "Dinosaurs_Park_ingles", "21": "Discovery_Ba\u00f1os", "22": "Discovery_ingles", "23": "El_Salado", "24": "El_Ventanal_Kong", "25": "Family_park", "26": "Free_places", "27": "Giratorio_precio", "28": "Information_banios", "29": "Los_ojos_volc\u00e1n_nido_del_aguila", "30": "Los_ojos_volc\u00e1n_precio", "31": "Los_pies_dios", "32": "Magic_Village_ingles", "33": "Museo_Fray_Enrique_Mideros", "34": "Museum_ingles", "35": "Parque_aventuras_San_Mart\u00edn", "36": "Parque_familia", "37": "PiQchur", "38": "PiQchur_ingles", "39": "Piscina_Virgen", "40": "Piscinas_Santa_Ana", "41": "Puentes", "42": "Sacha_360", "43": "Sacha_360_ingles", "44": "Salto_puente", "45": "Sanctuary_Our_Lady_Rosary", "46": "Santa_Clara", "47": "Santa_Clara_en", "48": "Santuario_Nuestra_Se\u00f1ora_Rosario", "49": "Swimming_Pools_Santa_Ana", "50": "Termas_dela_virgen", "51": "Termas_dela_virgen_en", "52": "The_Salado_thermal_pools", "53": "The_Window_Kong", "54": "The_eyes_volcano", "55": "The_god_feet", "56": "Torre_cristal", "57": "Troll_Mountain", "58": "Troll_Mountain_ingles", "59": "Virgin_Pool", "60": "Waterfall_agoyan", "61": "accountants", "62": "actividades_centro_banios", "63": "actividades_extremas", "64": "actividades_nocturnas", "65": "alquiler", "66": "atractivos", "67": "beso_de_la_luna_precio", "68": "besode_la_luna", "69": "besode_luna_horario", "70": "bosque_encantado", "71": "bot_challenge", "72": "bus_paths", "73": "cajeros_banios", "74": "casa_del_arbol", "75": "cascada_agoyan", "76": "cascada_virgen", "77": "cascadas", "78": "chamana", "79": "chamana_waterfall_ingles", "80": "chocolate_factory", "81": "city_trails_waks", "82": "clima", "83": "columpio_abismo_del_diablo", "84": "complaints", "85": "condor_flight", "86": "contabandistas", "87": "contestar_bien", "88": "contestar_mal", "89": "contrata_rafting", "90": "contratar_Canyoning", "91": "contrato_escaladaroca", "92": "cuesta_columpio_fantas\u00edas_Volar", "93": "cuesta_escalar", "94": "denuncias", "95": "despedida", "96": "devil_pailon", "97": "el_pailon", "98": "enchanted_forest", "99": "entrada_abismo", "100": "entrada_pailon_deldiablo", "101": "entrada_vuelodelcondor", "102": "escalada_roca", "103": "extreme", "104": "fabrica_chocolate", "105": "fantasias_volar", "106": "fantasias_volar_ingles", "107": "gastronomy_place", "108": "goodbye", "109": "greet", "110": "hands_of_god", "111": "hora_casaarbol", "112": "hora_zoo_san_martin", "113": "horarioCavernas", "114": "horarioLos_pies_dios", "115": "horarioPiQchur", "116": "horario_Aldea_Magica", "117": "horario_Dinosaurios_Park", "118": "horario_Parque_familia", "119": "horario_Sacha_360", "120": "horario_TrollMountain", "121": "horario_Ventanal_Kong", "122": "horario_animal_park", "123": "horario_discovery_ba\u00f1os", "124": "horario_fantas\u00edas_Volar", "125": "horario_manos_dios", "126": "horario_mirador_Bellavista", "127": "horario_parque_aventuras_San_Mart\u00edn", "128": "horarios_Cristo_Redentor", "129": "horarios_El_Salado", "130": "horarios_Museo_Fray_Enrique_Mideros", "131": "horarios_Piscina_Virgen", "132": "horarios_Piscinas_Santa_Ana", "133": "horarios_Santa_Clara", "134": "horarios_Termas_dela_virgen", "135": "horarios_Torre_cristal", "136": "horarios_bosque_encantado", "137": "horarios_cascada_pailon", "138": "horarios_chocolate", "139": "horarios_columpio_diablo", "140": "horarios_our_mundo_adventure", "141": "horarios_vuelo_condor", "142": "horariosvida_exotica", "143": "ines_maria_cascada", "144": "ines_maria_ingles", "145": "info_pondoa", "146": "inicio_mega_park", "147": "los_sauces", "148": "lugares_gastronomia", "149": "lunavolcan_trail", "150": "malecon_rioVerde", "151": "malecon_rioVerde_ingles", "152": "manos_de_dios", "153": "manto_dela_novia", "154": "map_Tourist", "155": "mapa", "156": "mas_info_alqui", "157": "medios_trasporte", "158": "mirador_Bellavista", "159": "mirador_Bellavista_ingles", "160": "mirador_virgen", "161": "miradores", "162": "mood_great", "163": "mood_unhappy", "164": "moon_kiss_mirador", "165": "museos", "166": "museums", "167": "nido_del_aguila_horario", "168": "night_activities", "169": "novia_waterfall", "170": "nuevos_atractivos", "171": "our_mundo_adventure", "172": "ourworldadventure_ingles", "173": "pacha_mama", "174": "pacha_mama_ingles", "175": "pachamama_horario", "176": "parques_tematicos", "177": "piscinas_banios", "178": "pondoa_trail", "179": "precioCavernas_Sigsi_Huayco", "180": "precioPiQchur", "181": "precioSacha_360", "182": "precioTroll_Mountain", "183": "precio_Aldea_Magica", "184": "precio_Balneario_Zu\u00f1ag", "185": "precio_Canyoning", "186": "precio_Cristo_Redentor", "187": "precio_Dinosaurios_Park", "188": "precio_El_Salado", "189": "precio_El_Ventanal_Kong", "190": "precio_Los_pies_dios", "191": "precio_Museo_Fray_Enrique_Mideros", "192": "precio_Parque_familia", "193": "precio_Piscinas_Santa_Ana", "194": "precio_Santa_Clara", "195": "precio_Termas_dela_virgen", "196": "precio_Torre_cristal", "197": "precio_animal_park", "198": "precio_antonio", "199": "precio_dios", "200": "precio_discovery_ba\u00f1os", "201": "precio_iglesia_ba\u00f1os", "202": "precio_mirador_Bellavista", "203": "precio_parque_aventuras_San_Mart\u00edn", "204": "precio_rafting", "205": "precios_Piscina_Virgen", "206": "precios_bosque_encantado", "207": "precios_cascada_virgen", "208": "precios_fabrica", "209": "precios_malecon_rioVerde", "210": "precios_manto_novia", "211": "precios_our_mundo_adventure", "212": "precios_san_martin", "213": "precios_vida_exotica", "214": "precticar_salto_puente", "215": "principales_famosos", "216": "punte_cristal", "217": "punte_cristal_ingles", "218": "que_eres", "219": "rafting", "220": "rafting_ingles", "221": "recomendaciones", "222": "recommendations", "223": "rock_climbing", "224": "ruta_lunavolcan", "225": "sal_inicial", "226": "salto_puente_valor", "227": "saludo", "228": "san_Antonio", "229": "san_Antonio_ingles", "230": "sendero_casa_arbol", "231": "senderos_ciudad", "232": "sincosto", "233": "sincosto_lugares", "234": "swimming", "235": "swings_text", "236": "tarifa_Precio_Mega_adventure_Park", "237": "tarifas_inesmaria", "238": "teller_banks", "239": "the_sauces_trail", "240": "thematic_parks", "241": "trayectos_buses", "242": "tree_house", "243": "tree_house_path", "244": "valor_casa_arbol", "245": "valor_cascada_chamana", "246": "valor_pachamama", "247": "valores_cascada_del_agoyan", "248": "vida_exotica", "249": "viewpoints_text", "250": "virgin_trail", "251": "virgin_waterfall", "252": "vuelo_del_condor", "253": "waterfall", "254": "weather", "255": "zoo_san_martin", "256": "zoo_san_martin_ingles", "257": "zoo_vidaExotica", "258": "zoological", "259": "zoologicos"}